{"stats":{"minecraft:picked_up":{"nefdecomod:shackles":2,"powersuits:tunnel_bore":1,"ava:ak12_unit_01":1},"minecraft:dropped":{"ava:ak12_unit_01":1},"minecraft:custom":{"minecraft:jump":44,"minecraft:time_since_rest":2891,"minecraft:deaths":1,"minecraft:damage_taken":420,"minecraft:crouch_one_cm":459,"minecraft:play_one_minute":31093,"minecraft:leave_game":3,"minecraft:sprint_one_cm":9731,"minecraft:time_since_death":2851,"minecraft:walk_one_cm":10533,"minecraft:sneak_time":477,"minecraft:fall_one_cm":5391,"minecraft:drop":1,"minecraft:fly_one_cm":90715},"minecraft:used":{"nefdecomod:creeper_plushie":1,"nefdecomod:dead_prisoner":5,"powersuits:tinkertable":1,"nefdecomod:zombie_plushie":1,"nefdecomod:shackles":1,"nefdecomod:worldmap_blue":1}},"DataVersion":2586}